[
    {
        "id": "jenlooper-cactus",
        "maker": "@jenlooper",
        "img": "https://raw.githubusercontent.com/jenlooper/jenlooper.github.io/main/images/cactus.jpg",
        "url": "https://jenlooper.github.io/cactus",
        "title": "The Quantified Cactus",
        "description": "A cactus that tells you when it needs water!"
    },
    {
        "id": "jenlooper-cactus-2",
        "maker": "@jenlooper",
        "img": "https://raw.githubusercontent.com/jenlooper/jenlooper.github.io/main/images/cactus.jpg",
        "url": "https://jenlooper.github.io/cactus",
        "title": "The Quantified Cactus 2",
        "description": "A cactus that tells you when it needs water!"
    },
    {
        "id": "jenlooper-cactus-3",
        "maker": "@jenlooper",
        "img": "https://raw.githubusercontent.com/jenlooper/jenlooper.github.io/main/images/cactus.jpg",
        "url": "https://jenlooper.github.io/cactus",
        "title": "The Quantified Cactus 3",
        "description": "A cactus that tells you when it needs water!"
    },
    {
        "id": "jenlooper-cactus-4",
        "maker": "@jenlooper",
        "img": "https://raw.githubusercontent.com/jenlooper/jenlooper.github.io/main/images/cactus.jpg",
        "url": "https://jenlooper.github.io/cactus",
        "title": "The Quantified Cactus 4",
        "description": "A cactus that tells you when it needs water!"
    },
    {
        "id": "jenlooper-cactus-5",
        "maker": "@jenlooper",
        "img": "https://raw.githubusercontent.com/jenlooper/jenlooper.github.io/main/images/cactus.jpg",
        "url": "https://jenlooper.github.io/cactus",
        "title": "The Quantified Cactus 5",
        "description": "A cactus that tells you when it needs water!"
    },
    {
        "id": "jenlooper-cactus-6",
        "maker": "@jenlooper",
        "img": "https://raw.githubusercontent.com/jenlooper/jenlooper.github.io/main/images/cactus.jpg",
        "url": "https://jenlooper.github.io/cactus",
        "title": "The Quantified Cactus 6",
        "description": "A cactus that tells you when it needs water!"
    },
    {
        "id": "jenlooper-cactus-7",
        "maker": "@jenlooper",
        "img": "https://raw.githubusercontent.com/jenlooper/jenlooper.github.io/main/images/cactus.jpg",
        "url": "https://jenlooper.github.io/cactus",
        "title": "The Quantified Cactus 7",
        "description": "A cactus that tells you when it needs water!"
    },
    {
        "id": "jenlooper-cactus-8",
        "maker": "@jenlooper",
        "img": "https://raw.githubusercontent.com/jenlooper/jenlooper.github.io/main/images/cactus.jpg",
        "url": "https://jenlooper.github.io/cactus",
        "title": "The Quantified Cactus 8",
        "description": "A cactus that tells you when it needs water!"
    },
    {
        "id": "jenlooper-cactus-9",
        "maker": "@jenlooper",
        "img": "https://raw.githubusercontent.com/jenlooper/jenlooper.github.io/main/images/cactus.jpg",
        "url": "https://jenlooper.github.io/cactus",
        "title": "The Quantified Cactus 9",
        "description": "A cactus that tells you when it needs water!"
    },
    {
        "id": "jenlooper-cactus-10",
        "maker": "@jenlooper",
        "img": "https://raw.githubusercontent.com/jenlooper/jenlooper.github.io/main/images/cactus.jpg",
        "url": "https://jenlooper.github.io/cactus",
        "title": "The Quantified Cactus 10",
        "description": "A cactus that tells you when it needs water!"
    },
    {
        "id": "jenlooper-cactus-11",
        "maker": "@jenlooper",
        "img": "https://raw.githubusercontent.com/jenlooper/jenlooper.github.io/main/images/cactus.jpg",
        "url": "https://jenlooper.github.io/cactus",
        "title": "The Quantified Cactus 11",
        "description": "A cactus that tells you when it needs water!"
    },
    {
        "id": "jenlooper-cactus-12",
        "maker": "@jenlooper",
        "img": "https://raw.githubusercontent.com/jenlooper/jenlooper.github.io/main/images/cactus.jpg",
        "url": "https://jenlooper.github.io/cactus",
        "title": "The Quantified Cactus 12",
        "description": "A cactus that tells you when it needs water!"
    },
    {
        "id": "jenlooper-cactus-13",
        "maker": "@jenlooper",
        "img": "https://raw.githubusercontent.com/jenlooper/jenlooper.github.io/main/images/cactus.jpg",
        "url": "https://jenlooper.github.io/cactus",
        "title": "The Quantified Cactus 13",
        "description": "A cactus that tells you when it needs water!"
    },
    {
        "id": "jenlooper-cactus-14",
        "maker": "@jenlooper",
        "img": "https://raw.githubusercontent.com/jenlooper/jenlooper.github.io/main/images/cactus.jpg",
        "url": "https://jenlooper.github.io/cactus",
        "title": "The Quantified Cactus 14",
        "description": "A cactus that tells you when it needs water!"
    },
    {
        "id": "jenlooper-cactus-15",
        "maker": "@jenlooper",
        "img": "https://raw.githubusercontent.com/jenlooper/jenlooper.github.io/main/images/cactus.jpg",
        "url": "https://jenlooper.github.io/cactus",
        "title": "The Quantified Cactus 15",
        "description": "A cactus that tells you when it needs water!"
    }
]